embedmeio/__init__.py
embedmeio/__main__.py
embedmeio/const.py
embedmeio-2024.12.0.dev7.dist-info/LICENSE
embedmeio-2024.12.0.dev7.dist-info/METADATA
embedmeio-2024.12.0.dev7.dist-info/WHEEL
embedmeio-2024.12.0.dev7.dist-info/entry_points.txt
embedmeio-2024.12.0.dev7.dist-info/top_level.txt
embedmeio-2024.12.0.dev7.dist-info/RECORD
