Metadata-Version: 2.1
Name: embedmeio
Version: 2024.12.0.dev7
Summary: Low-code embedded systems build tool
Author-email: "EmbedMe.io" <embedme@embedme.io>
License: MIT
Project-URL: Documentation, https://docs.embedme.io
Project-URL: Source Code, https://github.com/EmbedMe-io/embedme.git
Project-URL: Bug Tracker, https://github.com/EmbedMe-io/embedme/issues
Project-URL: Discord, https://discord.gg/egJ3ekJu
Keywords: home,automation
Platform: any
Classifier: Environment :: Console
Classifier: Intended Audience :: Developers
Classifier: Intended Audience :: End Users/Desktop
Classifier: License :: OSI Approved :: MIT License
Classifier: Programming Language :: C++
Classifier: Programming Language :: Python :: 3
Classifier: Topic :: Home Automation
Requires-Python: >=3.9.0
License-File: LICENSE
